dofusdude/__init__.py
dofusdude/api_client.py
dofusdude/api_response.py
dofusdude/configuration.py
dofusdude/exceptions.py
dofusdude/py.typed
dofusdude/rest.py
dofusdude/api/__init__.py
dofusdude/api/almanax_api.py
dofusdude/api/consumables_api.py
dofusdude/api/cosmetics_api.py
dofusdude/api/equipment_api.py
dofusdude/api/game_api.py
dofusdude/api/meta_api.py
dofusdude/api/mounts_api.py
dofusdude/api/quest_items_api.py
dofusdude/api/resources_api.py
dofusdude/api/sets_api.py
dofusdude/api/webhooks_api.py
dofusdude/models/__init__.py
dofusdude/models/almanax.py
dofusdude/models/almanax_bonus.py
dofusdude/models/almanax_tribute.py
dofusdude/models/almanax_tribute_item.py
dofusdude/models/almanax_webhook.py
dofusdude/models/almanax_webhook_daily_settings.py
dofusdude/models/condition.py
dofusdude/models/condition_leaf.py
dofusdude/models/condition_node.py
dofusdude/models/condition_relation.py
dofusdude/models/create_almanax_webhook.py
dofusdude/models/create_almanax_webhook_daily_settings.py
dofusdude/models/create_almanax_webhook_mentions_value_inner.py
dofusdude/models/create_rss_webhook.py
dofusdude/models/create_twitter_webhook.py
dofusdude/models/effect.py
dofusdude/models/effect_type.py
dofusdude/models/equipment.py
dofusdude/models/equipment_set.py
dofusdude/models/error.py
dofusdude/models/game_search.py
dofusdude/models/game_search_item.py
dofusdude/models/game_search_type.py
dofusdude/models/get_meta_almanax_bonuses200_response_inner.py
dofusdude/models/get_meta_webhooks_twitter200_response.py
dofusdude/models/images.py
dofusdude/models/item_subtype.py
dofusdude/models/list_equipment_set.py
dofusdude/models/list_equipment_sets.py
dofusdude/models/list_item.py
dofusdude/models/list_item_general.py
dofusdude/models/list_items.py
dofusdude/models/list_mounts.py
dofusdude/models/mount.py
dofusdude/models/mount_family.py
dofusdude/models/paged_links.py
dofusdude/models/put_almanax_webhook.py
dofusdude/models/put_rss_webhook.py
dofusdude-1.0.0.dist-info/METADATA
dofusdude-1.0.0.dist-info/WHEEL
dofusdude-1.0.0.dist-info/top_level.txt
dofusdude-1.0.0.dist-info/RECORD
