Metadata-Version: 2.1
Name: dofusdude
Version: 1.0.0
Summary: dofusdude
Home-page: https://github.com/dofusdude/dofusdude-py
Author: Survival
Author-email: stelzo@steado.de
License: GPL-3.0
Keywords: OpenAPI,OpenAPI-Generator,dofusdude
Requires-Dist: urllib3 <3.0.0,>=1.25.3
Requires-Dist: python-dateutil >=2.8.2
Requires-Dist: pydantic >=2
Requires-Dist: typing-extensions >=4.7.1
